uploadserver/__init__.py
uploadserver/__main__.py
uploadserver/cgi.py
uploadserver-6.0.0.dist-info/LICENSE
uploadserver-6.0.0.dist-info/METADATA
uploadserver-6.0.0.dist-info/WHEEL
uploadserver-6.0.0.dist-info/entry_points.txt
uploadserver-6.0.0.dist-info/top_level.txt
uploadserver-6.0.0.dist-info/RECORD
