Metadata-Version: 2.1
Name: uploadserver
Version: 6.0.0
Summary: Python's http.server extended to include a file upload page
Home-page: https://github.com/Densaugeo/uploadserver
Author: Densaugeo
Author-email: author@example.com
Classifier: Programming Language :: Python :: 3
Classifier: License :: OSI Approved :: MIT License
Classifier: Operating System :: OS Independent
Requires-Python: >=3.9
License-File: LICENSE
